willc/__init__.py
willc/main.py
willc-0.1.1.dist-info/LICENSE
willc-0.1.1.dist-info/METADATA
willc-0.1.1.dist-info/WHEEL
willc-0.1.1.dist-info/entry_points.txt
willc-0.1.1.dist-info/RECORD
