Metadata-Version: 2.1
Name: willc
Version: 0.1.1
Summary: My version of the `wc` tool
Home-page: https://github.com/WillDenby/willc
License: MIT
Author: WillDenby
Author-email: 119456795+WillDenby@users.noreply.github.com
Requires-Python: >=3.9,<4.0
Classifier: License :: OSI Approved :: MIT License
Classifier: Programming Language :: Python :: 3
Classifier: Programming Language :: Python :: 3.9
Classifier: Programming Language :: Python :: 3.10
Classifier: Programming Language :: Python :: 3.11
Classifier: Programming Language :: Python :: 3.12
Requires-Dist: pytest-cov (>=5.0.0,<6.0.0)
Requires-Dist: pytest-mock (>=3.14.0,<4.0.0)
Requires-Dist: ruff (>=0.4.4,<0.5.0)
Requires-Dist: typer (>=0.12.3,<0.13.0)
Project-URL: Repository, https://github.com/WillDenby/willc
